tensorqtl/__init__.py
tensorqtl/__main__.py
tensorqtl/cis.py
tensorqtl/coloc.py
tensorqtl/core.py
tensorqtl/eigenmt.py
tensorqtl/genotypeio.py
tensorqtl/mixqtl.py
tensorqtl/pgen.py
tensorqtl/post.py
tensorqtl/rfunc.py
tensorqtl/susie.py
tensorqtl/tensorqtl.py
tensorqtl/trans.py
tensorqtl-1.0.10.dist-info/LICENSE
tensorqtl-1.0.10.dist-info/METADATA
tensorqtl-1.0.10.dist-info/WHEEL
tensorqtl-1.0.10.dist-info/top_level.txt
tensorqtl-1.0.10.dist-info/RECORD
