Metadata-Version: 2.1
Name: tensorqtl
Version: 1.0.10
Summary: GPU-accelerated QTL mapper
Author-email: Francois Aguet <francois@broadinstitute.org>
Maintainer-email: Francois Aguet <francois@broadinstitute.org>
License: BSD 3-Clause License
Project-URL: Repository, https://github.com/broadinstitute/tensorqtl.git
Keywords: Quantitative trait loci
Classifier: Development Status :: 4 - Beta
Classifier: Programming Language :: Python :: 3
Classifier: Intended Audience :: Science/Research
Classifier: Topic :: Scientific/Engineering :: Bio-Informatics
License-File: LICENSE
Requires-Dist: numpy
Requires-Dist: pandas
Requires-Dist: Pgenlib >=0.90.1
Requires-Dist: qtl
Requires-Dist: scipy
Requires-Dist: torch
